guardshield/__init__.py
guardshield/dll_bytes.py
guardshield/main.py
guardshield-1.0.4.dist-info/LICENSE
guardshield-1.0.4.dist-info/METADATA
guardshield-1.0.4.dist-info/WHEEL
guardshield-1.0.4.dist-info/top_level.txt
guardshield-1.0.4.dist-info/RECORD
