Metadata-Version: 2.1
Name: guardshield
Version: 1.0.4
Summary: Security lib
Home-page: https://github.com/OxynDev/ExcerSec
Author: Oxyn
Author-email: oxyn.dev@gmail.com
License: MIT
Keywords: python anti debugger security exe
Platform: UNKNOWN
